arcadepy/__init__.py
arcadepy/_base_client.py
arcadepy/_client.py
arcadepy/_compat.py
arcadepy/_constants.py
arcadepy/_exceptions.py
arcadepy/_files.py
arcadepy/_models.py
arcadepy/_qs.py
arcadepy/_resource.py
arcadepy/_response.py
arcadepy/_streaming.py
arcadepy/_types.py
arcadepy/_version.py
arcadepy/pagination.py
arcadepy/py.typed
arcadepy/_utils/__init__.py
arcadepy/_utils/_compat.py
arcadepy/_utils/_datetime_parse.py
arcadepy/_utils/_logs.py
arcadepy/_utils/_proxy.py
arcadepy/_utils/_reflection.py
arcadepy/_utils/_resources_proxy.py
arcadepy/_utils/_streams.py
arcadepy/_utils/_sync.py
arcadepy/_utils/_transform.py
arcadepy/_utils/_typing.py
arcadepy/_utils/_utils.py
arcadepy/lib/.keep
arcadepy/resources/__init__.py
arcadepy/resources/auth.py
arcadepy/resources/health.py
arcadepy/resources/workers.py
arcadepy/resources/admin/__init__.py
arcadepy/resources/admin/admin.py
arcadepy/resources/admin/auth_providers.py
arcadepy/resources/admin/secrets.py
arcadepy/resources/admin/user_connections.py
arcadepy/resources/chat/__init__.py
arcadepy/resources/chat/chat.py
arcadepy/resources/chat/completions.py
arcadepy/resources/tools/__init__.py
arcadepy/resources/tools/formatted.py
arcadepy/resources/tools/scheduled.py
arcadepy/resources/tools/tools.py
arcadepy/types/__init__.py
arcadepy/types/auth_authorize_params.py
arcadepy/types/auth_confirm_user_params.py
arcadepy/types/auth_status_params.py
arcadepy/types/chat_message.py
arcadepy/types/chat_message_param.py
arcadepy/types/chat_response.py
arcadepy/types/choice.py
arcadepy/types/confirm_user_response.py
arcadepy/types/execute_tool_response.py
arcadepy/types/health_schema.py
arcadepy/types/tool_authorize_params.py
arcadepy/types/tool_definition.py
arcadepy/types/tool_execute_params.py
arcadepy/types/tool_execution.py
arcadepy/types/tool_execution_attempt.py
arcadepy/types/tool_get_params.py
arcadepy/types/tool_get_response.py
arcadepy/types/tool_list_params.py
arcadepy/types/tool_list_response.py
arcadepy-1.10.0.dist-info/METADATA
arcadepy-1.10.0.dist-info/WHEEL
arcadepy-1.10.0.dist-info/licenses/LICENSE
arcadepy-1.10.0.dist-info/RECORD
